blechpy/__init__.py
blechpy/environment.yml
blechpy/analysis/__init__.py
blechpy/analysis/blech_clustering.py
blechpy/analysis/circus_interface.py
blechpy/analysis/clustering.py
blechpy/analysis/held_unit_analysis.py
blechpy/analysis/palatability_analysis.py
blechpy/analysis/poissonHMM.py
blechpy/analysis/poissonHMM_deprecated.py
blechpy/analysis/spike_analysis.py
blechpy/analysis/spike_detection.py
blechpy/analysis/spike_sorting.py
blechpy/analysis/stat_tests.py
blechpy/analysis/defaults/bilateral32.prb
blechpy/analysis/defaults/default_config.params
blechpy/datastructures/__init__.py
blechpy/datastructures/dataset.py
blechpy/datastructures/experiment.py
blechpy/datastructures/objects.py
blechpy/datastructures/project.py
blechpy/dio/__init__.py
blechpy/dio/blech_params.py
blechpy/dio/h5io.py
blechpy/dio/hmmIO.py
blechpy/dio/load_intan_rhd_format.py
blechpy/dio/rawIO.py
blechpy/dio/defaults/CAR_params.json
blechpy/dio/defaults/clustering_params.json
blechpy/dio/defaults/pal_id_params.json
blechpy/dio/defaults/psth_params.json
blechpy/dio/defaults/spike_array_params.json
blechpy/dio/intanutil/__init__.py
blechpy/dio/intanutil/data_to_result.py
blechpy/dio/intanutil/get_bytes_per_data_block.py
blechpy/dio/intanutil/notch_filter.py
blechpy/dio/intanutil/qstring.py
blechpy/dio/intanutil/read_header.py
blechpy/dio/intanutil/read_one_data_block.py
blechpy/plotting/__init__.py
blechpy/plotting/blech_waveforms_datashader.py
blechpy/plotting/data_plot.py
blechpy/plotting/hmm_plot.py
blechpy/plotting/palatability_plot.py
blechpy/utils/__init__.py
blechpy/utils/cluster_filters.py
blechpy/utils/data_reset.py
blechpy/utils/decorators.py
blechpy/utils/math_tools.py
blechpy/utils/memory_monitor.py
blechpy/utils/particles.py
blechpy/utils/print_tools.py
blechpy/utils/spike_sorting_GUI.py
blechpy/utils/tk_widgets.py
blechpy/utils/userIO.py
blechpy/utils/write_tools.py
blechpy-2.2.14.dist-info/LICENSE
blechpy-2.2.14.dist-info/METADATA
blechpy-2.2.14.dist-info/WHEEL
blechpy-2.2.14.dist-info/top_level.txt
blechpy-2.2.14.dist-info/RECORD
