Metadata-Version: 2.1
Name: blechpy
Version: 2.2.14
Summary: Package for exrtacting, processing and analyzing Intan and OpenEphys data
Home-page: https://github.com/nubs01/blechpy
Author: Roshan Nanu, Daniel Svedberg
Author-email: roshan.nanu@gmail.com, dan.ake.svedberg@gmail.com
License: UNKNOWN
Keywords: blech katz_lab Intan electrophysiology neuroscience
Platform: UNKNOWN
Classifier: Programming Language :: Python :: 3.6
Classifier: Programming Language :: Python :: 3.7
Classifier: License :: OSI Approved :: MIT License
Requires-Python: >=3.6
License-File: LICENSE
Requires-Dist: easygui (>=0.98.1)
Requires-Dist: tables (>=3.5.1)
Requires-Dist: numpy (==1.18.5)
Requires-Dist: datashader (<=0.10.0,>=0.6.9)
Requires-Dist: scipy (<1.4,>=1.2.1)
Requires-Dist: scikit-learn (>=0.20.3)
Requires-Dist: tqdm (>=4.36.1)
Requires-Dist: numba (==0.48.0)
Requires-Dist: matplotlib (==3.0.3)
Requires-Dist: pygments
Requires-Dist: mistune (>=0.8.1)
Requires-Dist: ipython (>=5.0.0)
Requires-Dist: jupyter-core (>=4.4.0)
Requires-Dist: entrypoints (>=0.2.2)
Requires-Dist: umap-learn (>=0.3.10)
Requires-Dist: holoviews (>=1.12.7)
Requires-Dist: h5py (>=2.10.0)
Requires-Dist: statsmodels
Requires-Dist: seaborn
Requires-Dist: appdirs (>=1.4.3)
Requires-Dist: joblib (>=1.1.0)
Requires-Dist: prompt-toolkit (==3.0.3)
Requires-Dist: pywavelets (>=1.1.1)
Requires-Dist: imageio (>=2.5.0)
Requires-Dist: PyYAML (==5.4)
Requires-Dist: numexpr (<=2.8.4)
Requires-Dist: pyBAKS (>=0.1.6)
